{
    "type": "FeatureCollection",
    "features": [
      {
        "type": "Feature",
        "properties": {
          "name": "Salt Lake City"
        },
        "geometry": {
          "type": "Point",
          "coordinates": [-111.8910, 40.7608]
        }
      },
      {
        "type": "Feature",
        "properties": {
          "name": "Park City"
        },
        "geometry": {
          "type": "Point",
          "coordinates": [-111.4979, 40.6461]
        }
      },
      {
        "type": "Feature",
        "properties": {
          "name": "Provo"
        },
        "geometry": {
          "type": "Point",
          "coordinates": [-111.6585, 40.2338]
        }
      },
      {
        "type": "Feature",
        "properties": {
          "name": "Ogden"
        },
        "geometry": {
          "type": "Point",
          "coordinates": [-111.9738, 41.2230]
        }
      }
    ]
  }
  